enchante/__init__.py
enchante/__main__.py
enchante/main.py
enchante/templates/table/__init__.py.jinja
enchante/templates/table/crud.py.jinja
enchante/templates/table/model.py.jinja
enchante/templates/table/schema.py.jinja
enchante/utils/__init__.py
enchante/utils/base.py
enchante/utils/config.py
enchante/utils/crud.py
enchante/utils/partial.py
enchante-0.3.0.dist-info/LICENSE
enchante-0.3.0.dist-info/METADATA
enchante-0.3.0.dist-info/WHEEL
enchante-0.3.0.dist-info/entry_points.txt
enchante-0.3.0.dist-info/RECORD
