Metadata-Version: 2.1
Name: enchante
Version: 0.3.0
Summary: CLI tool to help scaffolding relational DB architecture as code
License: MIT
Author: Steven John
Author-email: steven@stevenjohn.co
Requires-Python: >=3.10
Classifier: License :: OSI Approved :: MIT License
Classifier: Programming Language :: Python :: 3
Classifier: Programming Language :: Python :: 3.10
Classifier: Programming Language :: Python :: 3.11
Classifier: Programming Language :: Python :: 3.12
Requires-Dist: SQLAlchemy (>=2.0,<3.0)
Requires-Dist: alembic (>=1.11.1,<2.0.0)
Requires-Dist: jinja2 (>=3.1.4,<4.0.0)
Requires-Dist: pydantic (>=2.1.1,<3.0.0)
Requires-Dist: pyhumps (>=3.8.0,<4.0.0)
Requires-Dist: pyyaml (>=6.0.1,<7.0.0)
Requires-Dist: rich (>=13.7.1,<14.0.0)
Requires-Dist: typer (>=0.9.0)
